numeroprimo/__init__.py
numeroprimo/numeroprimo.py
numeroprimo-1.0.dist-info/LICENSE
numeroprimo-1.0.dist-info/METADATA
numeroprimo-1.0.dist-info/WHEEL
numeroprimo-1.0.dist-info/top_level.txt
numeroprimo-1.0.dist-info/RECORD
