Metadata-Version: 2.1
Name: numeroprimo
Version: 1.0
Summary: Herramienta para saber si un número es primo.
Home-page: UNKNOWN
Author: Lucy Areán
Author-email: lucy.arean.granja@gmail.com
License: GNU GPLv3
Keywords: pyoperaciones primo número
Platform: UNKNOWN
Classifier: Development Status :: 4 - Beta
Classifier: Intended Audience :: Developers
Classifier: Topic :: Utilities
Classifier: License :: OSI Approved :: GNU General Public License v3 (GPLv3)
Classifier: Programming Language :: Python :: 3
Classifier: Operating System :: OS Independent
